<?xml version="1.0" encoding="UTF-8"?><record_update>
    <sys_choice action="DELETE" field="u_what_needed" table="x_58872_needit_needit" version="3">
        <sys_choice_set action="DELETE">
            <element>u_what_needed</element>
            <name>x_58872_needit_needit</name>
            <sys_class_name/>
            <sys_created_by/>
            <sys_created_on/>
            <sys_id/>
            <sys_mod_count/>
            <sys_name/>
            <sys_package/>
            <sys_policy/>
            <sys_scope/>
            <sys_update_name/>
            <sys_updated_by/>
            <sys_updated_on>2020-04-12 19:27:26</sys_updated_on>
        </sys_choice_set>
    </sys_choice>
    <sys_update_version action="INSERT_OR_UPDATE">
        <action>DELETE</action>
        <application/>
        <file_path/>
        <instance_id>0f08158bdb5236800e785d00cf96198d</instance_id>
        <instance_name>dev35390</instance_name>
        <name>sys_choice_x_58872_needit_needit_u_what_needed</name>
        <payload><![CDATA[<?xml version="1.0" encoding="UTF-8"?><record_update><sys_choice action="DELETE" field="u_what_needed" table="x_58872_needit_needit" version="3"><sys_choice_set action="DELETE"><element>u_what_needed</element><name>x_58872_needit_needit</name><sys_class_name/><sys_created_by/><sys_created_on/><sys_id/><sys_mod_count/><sys_name/><sys_package/><sys_policy/><sys_scope/><sys_update_name/><sys_updated_by/><sys_updated_on>2020-04-12 19:27:26</sys_updated_on></sys_choice_set></sys_choice></record_update>]]></payload>
        <payload_hash>-429457270</payload_hash>
        <record_name>x_58872_needit_needit.u_what_needed</record_name>
        <reverted_from/>
        <source>ecbb4d722f00101061c4808cf699b646</source>
        <source_table>sys_update_set</source_table>
        <state>previous</state>
        <sys_created_by>admin</sys_created_by>
        <sys_created_on>2020-04-12 19:27:26</sys_created_on>
        <sys_id>7b2fbc832f48101061c4808cf699b66e</sys_id>
        <sys_mod_count>0</sys_mod_count>
        <sys_recorded_at>1716fdc64530000001</sys_recorded_at>
        <sys_updated_by>admin</sys_updated_by>
        <sys_updated_on>2020-04-12 19:27:26</sys_updated_on>
        <type>Choice list</type>
        <update_guid>f32fbc83db481010e54cdca7f67e076e</update_guid>
        <update_guid_history>f32fbc83db481010e54cdca7f67e076e:-429457270,bf2fbc8347481010e293b2d4f88df46a:-1645599408,3f2fbc831c4810108caa2590c9dd7a67:872629236,bb2fbc837148101086c34c3bec375d64:-1368518222,3b2fbc836348101079cebcf607f26c61:-835683595,b72fbc8338481010bda7fa97c256fa5e:1301214599,372fbc83d0481010aae3e114c54d1b5b:-217878606,b32fbc835f481010d0d93d9c98d86f58:391391694,4f1859fa940010101421284caadac974:282754765</update_guid_history>
    </sys_update_version>
    <sys_metadata_delete action="INSERT_OR_UPDATE">
        <sys_audit_delete/>
        <sys_class_name>sys_metadata_delete</sys_class_name>
        <sys_created_by>admin</sys_created_by>
        <sys_created_on>2020-04-12 19:27:35</sys_created_on>
        <sys_db_object display_value="" name="sys_choice_set">sys_choice_set</sys_db_object>
        <sys_id>313f30c32f48101061c4808cf699b631</sys_id>
        <sys_metadata>313f30c32f48101061c4808cf699b631</sys_metadata>
        <sys_mod_count>0</sys_mod_count>
        <sys_name>u_what_needed</sys_name>
        <sys_package display_value="NeedIt" source="x_58872_needit">6ead8e780f603200cd674f8ce1050ed1</sys_package>
        <sys_parent/>
        <sys_policy/>
        <sys_scope display_value="NeedIt">6ead8e780f603200cd674f8ce1050ed1</sys_scope>
        <sys_scope_delete display_value="">94872a8897db403e8ee69a431de2fca4</sys_scope_delete>
        <sys_update_name>sys_choice_x_58872_needit_needit_u_what_needed</sys_update_name>
        <sys_update_version display_value="sys_choice_x_58872_needit_needit_u_what_needed">7b2fbc832f48101061c4808cf699b66e</sys_update_version>
        <sys_updated_by>admin</sys_updated_by>
        <sys_updated_on>2020-04-12 19:27:35</sys_updated_on>
    </sys_metadata_delete>
</record_update>
